haoqiren_py_win32/base/winpath.cp36-win32.pyd
haoqiren_py_win32/base/winver.cp36-win32.pyd
haoqiren_py_win32/gui/guihelper.cp36-win32.pyd
haoqiren_py_win32/office/msoffice/excel/xlapp.cp36-win32.pyd
haoqiren_py_win32/office/msoffice/excel/xlconstant.cp36-win32.pyd
haoqiren_py_win32/office/msoffice/excel/xlrange.cp36-win32.pyd
haoqiren_py_win32/office/msoffice/excel/xlwindow.cp36-win32.pyd
haoqiren_py_win32/office/msoffice/excel/xlworkbook.cp36-win32.pyd
haoqiren_py_win32/office/msoffice/excel/xlworksheet.cp36-win32.pyd
haoqiren_py_win32/office/msoffice/word/wdapp.cp36-win32.pyd
haoqiren_py_win32/office/msoffice/word/wdconstant.cp36-win32.pyd
haoqiren_py_win32/office/msoffice/word/wddocument.cp36-win32.pyd
haoqiren_py_win32/office/msoffice/word/wdheaderfooter.cp36-win32.pyd
haoqiren_py_win32/office/msoffice/word/wdparagraph.cp36-win32.pyd
haoqiren_py_win32/office/msoffice/word/wdrange.cp36-win32.pyd
haoqiren_py_win32/office/msoffice/word/wdsection.cp36-win32.pyd
haoqiren_py_win32/office/msoffice/word/wdtable.cp36-win32.pyd
haoqiren_py_win32/office/xlwings/xlapp.cp36-win32.pyd
haoqiren_py_win32_ext-0.0.8.dist-info/METADATA
haoqiren_py_win32_ext-0.0.8.dist-info/WHEEL
haoqiren_py_win32_ext-0.0.8.dist-info/top_level.txt
haoqiren_py_win32_ext-0.0.8.dist-info/RECORD
