Metadata-Version: 2.1
Name: haoqiren-py-win32-ext
Version: 0.0.8
Summary: The HaoQiRen Python Win32 Functions
Home-page: http://www.haoqiren.com
Author: HaoQiRen
Author-email: haoqiren@qq.com
Maintainer: HaoQiRen
Maintainer-email: haoqiren@qq.com
License: MIT
Download-URL: http://www.haoqiren.com
Project-URL: Documentation, http://www.haoqiren.com
Project-URL: Source, http://www.haoqiren.com
Keywords: tool utils lib win32
Platform: win32
Platform: win_amd64
Classifier: License :: OSI Approved :: MIT License
Classifier: Programming Language :: Python :: 3.6
Requires-Python: >=3.6.8
Requires-Dist: haoqiren-py-ext (==0.0.8)
Requires-Dist: pywin32
Requires-Dist: xlwings
